llmfuncs/__init__.py
llmfuncs/schema.py
llmfuncs/tool.py
llmfuncs/validator.py
llmfuncs-0.2.3.dist-info/LICENSE
llmfuncs-0.2.3.dist-info/METADATA
llmfuncs-0.2.3.dist-info/WHEEL
llmfuncs-0.2.3.dist-info/top_level.txt
llmfuncs-0.2.3.dist-info/RECORD
