Metadata-Version: 2.1
Name: llmfuncs
Version: 0.2.3
Summary: Dynamically generate JSON Schema from Python code.
Home-page: https://github.com/FyZyX/llmfuncs
Author: Lucas Lofaro
Author-email: lucasmlofaro@gmail.com
License: MIT
License-File: LICENSE
Requires-Dist: docstring-parser (~=0.15)
Requires-Dist: jsonschema (~=4.17.3)
